criteo_api_retailmedia_v2025_10/__init__.py
criteo_api_retailmedia_v2025_10/api_client.py
criteo_api_retailmedia_v2025_10/api_client_builder.py
criteo_api_retailmedia_v2025_10/configuration.py
criteo_api_retailmedia_v2025_10/criteo_api_client.py
criteo_api_retailmedia_v2025_10/criteo_auth.py
criteo_api_retailmedia_v2025_10/criteo_rest.py
criteo_api_retailmedia_v2025_10/exceptions.py
criteo_api_retailmedia_v2025_10/flow_constants.py
criteo_api_retailmedia_v2025_10/model_utils.py
criteo_api_retailmedia_v2025_10/rest.py
criteo_api_retailmedia_v2025_10/api/__init__.py
criteo_api_retailmedia_v2025_10/api/accounts_api.py
criteo_api_retailmedia_v2025_10/api/analytics_api.py
criteo_api_retailmedia_v2025_10/api/audience_api.py
criteo_api_retailmedia_v2025_10/api/balance_api.py
criteo_api_retailmedia_v2025_10/api/billing_api.py
criteo_api_retailmedia_v2025_10/api/campaign_api.py
criteo_api_retailmedia_v2025_10/api/gateway_api.py
criteo_api_retailmedia_v2025_10/apis/__init__.py
criteo_api_retailmedia_v2025_10/model/__init__.py
criteo_api_retailmedia_v2025_10/model/account_fees_search_request.py
criteo_api_retailmedia_v2025_10/model/account_fees_update_request.py
criteo_api_retailmedia_v2025_10/model/add_funds_to_balance_v2.py
criteo_api_retailmedia_v2025_10/model/add_funds_to_balance_v2_request.py
criteo_api_retailmedia_v2025_10/model/add_remove_keyword_model.py
criteo_api_retailmedia_v2025_10/model/add_remove_keywords_model.py
criteo_api_retailmedia_v2025_10/model/add_remove_keywords_model_request.py
criteo_api_retailmedia_v2025_10/model/add_remove_keywords_model_resource.py
criteo_api_retailmedia_v2025_10/model/add_to_basket_ids_update_model202110.py
criteo_api_retailmedia_v2025_10/model/add_to_basket_ids_update_model202110_request.py
criteo_api_retailmedia_v2025_10/model/add_to_basket_target202110.py
criteo_api_retailmedia_v2025_10/model/add_to_basket_target202110_request.py
criteo_api_retailmedia_v2025_10/model/add_to_basket_target202110_response.py
criteo_api_retailmedia_sdk-2025.10.0.251229.dist-info/METADATA
criteo_api_retailmedia_sdk-2025.10.0.251229.dist-info/WHEEL
criteo_api_retailmedia_sdk-2025.10.0.251229.dist-info/top_level.txt
criteo_api_retailmedia_sdk-2025.10.0.251229.dist-info/RECORD
