Metadata-Version: 2.4
Name: criteo-api-retailmedia-sdk
Version: 2025.10.0.251229
Summary: Criteo API SDK
Home-page: https://github.com/criteo/criteo-api-python-sdk
Author: Criteo
Author-email: 
Keywords: Criteo,OpenAPI-Generator,Criteo API SDK
Classifier: Development Status :: 4 - Beta
Classifier: Intended Audience :: Developers
Classifier: License :: OSI Approved :: Apache Software License
Classifier: Natural Language :: English
Classifier: Operating System :: OS Independent
Classifier: Topic :: Software Development :: Libraries
Requires-Python: >=3.6
Requires-Dist: urllib3>=1.25.3
Requires-Dist: python-dateutil
Dynamic: author
Dynamic: classifier
Dynamic: description
Dynamic: description-content-type
Dynamic: home-page
Dynamic: keywords
Dynamic: requires-dist
Dynamic: requires-python
Dynamic: summary
